LICENSE
MANIFEST.in
README.md
requirements.txt
setup.cfg
setup.py
tiempo/__init__.py
tiempo/conf.py
tiempo/conn.py
tiempo/dashboard.py
tiempo/exceptions.py
tiempo/execution.py
tiempo/task.py
tiempo/utils.py
tiempo.egg-info/PKG-INFO
tiempo.egg-info/SOURCES.txt
tiempo.egg-info/dependency_links.txt
tiempo.egg-info/requires.txt
tiempo.egg-info/top_level.txt
tiempo/contrib/__init__.py
tiempo/contrib/django_app/__init__.py
tiempo/contrib/django_app/models.py
tiempo/contrib/django_app/urls.py
tiempo/contrib/django_app/views.py
tiempo/contrib/django_app/templates/tiempo/all_tasks.html
tiempo/contrib/django_app/templates/tiempo/dashboard.html
tiempo/contrib/django_app/templates/tiempo/recent.html
tiempo/contrib/django_app/utils/__init__.py
tiempo/contrib/django_app/utils/loader.py
tiempo/contrib/django_app/utils/six.py
tiempo/demo/__init__.py
tiempo/demo/tasks.py
tiempo/scripts/metronome
tiempo/templates/400.html
tiempo/templates/403.html
tiempo/templates/404.html
tiempo/templates/500.html
tiempo/templates/base.html
tiempo/templates/error.html
tiempo/templates/main.html
tiempo/tests/__init__.py
tiempo/tests/sample_tasks.py
tiempo/tests/test_dequeue.py
tiempo/tests/test_startup.py
tiempo/tests/totally_weird.py
tiempo/web/__init__.py
tiempo/web/resource.py
tiempo/web/service.py
tiempo/web/shortcuts.py