Metadata-Version: 1.1
Name: tiempo
Version: 1.2.1
Summary: Twisted task scheduling for django
Home-page: https://github.com/hangarunderground/tiempo
Author: Damon
Author-email: UNKNOWN
License: UNKNOWN
Keywords: twisted,tasks,redis,scheduling
Platform: UNKNOWN
Classifier: Intended Audience :: Developers
Classifier: Natural Language :: English
Classifier: Operating System :: OS Independent
Classifier: Programming Language :: Python
